Metadata-Version: 2.1
Name: planetmint-driver-python
Version: 0.18.2
Summary: Python driver for Planetmint
License: AGPLv3-or-later
Author: Your Name
Author-email: you@example.com
Requires-Python: >=3.9,<4.0
Classifier: License :: Other/Proprietary License
Classifier: Programming Language :: Python :: 3
Classifier: Programming Language :: Python :: 3.9
Classifier: Programming Language :: Python :: 3.10
Classifier: Programming Language :: Python :: 3.11
Requires-Dist: planetmint-ipld (>=0.0.3,<0.0.4)
Requires-Dist: planetmint-transactions (>=0.8.0,<0.9.0)
Requires-Dist: pysha3 (>=1.0.2,<2.0.0)
Requires-Dist: python-rapidjson (>=1.9,<2.0)
Requires-Dist: python-rapidjson-schema (>=0.1.1,<0.2.0)
Requires-Dist: requests (>=2.28.2,<3.0.0)
Requires-Dist: sphinx-press-theme (==0.8.0)
Requires-Dist: wheel (>=0.38.1,<0.39.0)
